LICENCE
README.md
setup.py
eunice/__init__.py
eunice/__main__.py
eunice/args.py
eunice/cmdline.py
eunice/definitions.py
eunice/eunice_logging.py
eunice/models.py
eunice/run.py
eunice/utils.py
eunice.egg-info/PKG-INFO
eunice.egg-info/SOURCES.txt
eunice.egg-info/dependency_links.txt
eunice.egg-info/entry_points.txt
eunice.egg-info/not-zip-safe
eunice.egg-info/requires.txt
eunice.egg-info/top_level.txt